geosky/cities.json
geosky/geo_plug.py
geosky-1.0.9.dist-info/LICENSE
geosky-1.0.9.dist-info/METADATA
geosky-1.0.9.dist-info/WHEEL
geosky-1.0.9.dist-info/top_level.txt
geosky-1.0.9.dist-info/RECORD
