Metadata-Version: 2.1
Name: geosky
Version: 1.0.9
Summary: A Python package to get all city country and stat names
Home-page: https://github.com/jyotiprakash-work/geosky
Author: jyotiprakash panigrahi
Author-email: jyotiprakash.work@gmail.com
License: MIT
Platform: UNKNOWN
Classifier: License :: OSI Approved :: MIT License
Classifier: Programming Language :: Python :: 3
Classifier: Programming Language :: Python :: 3.5
Requires-Dist: requests
